{"album_uri": ["spotify:album:4gR3h0hcpE1iJH0v5bVv78", "spotify:album:5MS3MvWHJ3lOZPLiMxzOU6", "spotify:album:59hIIDzaPSH5O3QSz4zX0t", "spotify:album:5MnLj1SQmw3nr7oTbJgtuB", "spotify:album:0FYvMdfTfYJxnJnKs1wDb0", "spotify:album:1POWgdYTzfFt9rhKlXFwsU", "spotify:album:1HTdVIlFgO8o2Oby5rdXs0", "spotify:album:4yrzsGF0xjnXP5oWNvMNqX", "spotify:album:2FD6g8bXEn2uQMYbeqqoCg", "spotify:album:5qPgB3OSDv3KfALFg1PZwe", "spotify:album:50DbtjQmnPnB92Mf7yxQt4", "spotify:album:2XlxXuumhYX4lIU2nXoUXw", "spotify:album:1nP2b8dTaVUvvAOyRbDoBe", "spotify:album:32FRll0ejOVNcspDDtUEqY", "spotify:album:3mYhUHiupqEamB1Qkl9ejL", "spotify:album:3jDmDOYQ3fN2XDqO9euRD5", "spotify:album:73wpA6cBZPGR7MFFLet4xz", "spotify:album:0gBApcXn5P14zuoBj27Uxd", "spotify:album:4LDKeMhuzPUzekNfeWrzRl", "spotify:album:2K2es8pRFX0kOaEdXZZgMl", "spotify:album:6ZDt6HZAFajVtwvNOjJb2b", "spotify:album:3s4uzffoGode9dbtELaVEp", "spotify:album:11KPzNJd5GlFhb1R11cZVr", "spotify:album:7IdlBOwOeXlriuPRozrkKz", "spotify:album:4JUp6qReEgKfOP76grq6v0", "spotify:album:3LSep2wdPolkSYoB1QB7IV", "spotify:album:2clsCCVAKCSc7PcwJ7uFLW", "spotify:album:49OQ6tF3eo3Fdgp3GMhHep", "spotify:album:4I00tpvL54vnWy49vH5fRK", "spotify:album:54x77I85ZNITP0wvN07CVT", "spotify:album:43AaQNHNlJlf8F2iQkivyx", "spotify:album:0A4xJz6OAedAQGriJH7pjn", "spotify:album:6v0yp2gWW4rFao7LtIA8RR", "spotify:album:1oKYKiAwR31eJvkRwpQVrb", "spotify:album:5Co3CGD9lBQVNnn7q0px1g", "spotify:album:5o1xUBd8aM7qFhjlBXiIpb", "spotify:album:4Lo6GJMW4ctfhtuCqMkn1O", "spotify:album:07AiRVrtrniKqkxHpLLY2g", "spotify:album:1ia27ME4iQkoIyUHBnJqX6", "spotify:album:5LZiWbqOpj6g8uxSHch12S", "spotify:album:3SxiMoJROq0kvfbQtd75xp", "spotify:album:0S180TSjO1KVmxh4oZHimt"], "album_name": ["HEROES & VILLAINS", "Her Loss", "Only Built For Infinity Links", "FTCU (feat. GloRilla & Gangsta Boo)", "It's Only Me", "Pink Heartz", "No More Leaks", "Letter to Takeoff", "Just Wanna Rock", "Do It Again (feat. 2Rare)", "PRE5L", "Ain\u2019t Safe (feat. Don Toliver)", "Stop Breathing", "Get Away", "90 Days", "Bag Talk", "Break My Heart", "Blackout", "Who is Nardo Wick?? (Deluxe)", "One Mic, One Gun", "Take Shots (feat. Tory Lanez)", "ONLY BUILT 4 DIAMOND LINKS", "Survivor\u2019s Remorse: A Side", "Twin (feat. Lil Durk)", "It's Not Me It's You (Deluxe)", "BET", "My Friends (feat. Lil Durk)", "Give You What You Want", "In My Head", "Walk/Spin", "2 Mins of Pain (feat. Alborosie)", "I Never Felt Nun", "Do It Right", "Bye Bye", "The Melodic Blue (Deluxe)", "Tomorrow 2 (with Cardi B)", "Nothing Changed", "Blow", "Queen Radio: Volume 1", "Poland", "Down In Atlanta", "OOGA BOOGA!"], "artist_uri": ["spotify:artist:0iEtIxbK0KxaSlF7G42ZOp", "spotify:artist:3TVXtAsR1Inumwj472S9r4", "spotify:artist:0VRj0yCOv2FXJNP47XQnx5", "spotify:artist:3MdXrJWsbVzdn6fe5JYkSQ", "spotify:artist:5f7VJjfbwm532GiveGC0ZK", "spotify:artist:2SJhf6rTOU53g8yBdAjPby", "spotify:artist:5H4yInM5zmHqpKIoMNAx4r", "spotify:artist:13y7CgLHjMVRMDqxdx0Xdo", "spotify:artist:4O15NlyKLIASxsJ0PrXPfz", "spotify:artist:0ErzCpIMyLcjPiwT4elrtZ", "spotify:artist:0RESbWvOMyua0yuyVrztJ5", "spotify:artist:6Xgp2XMz1fhVYe7i6yNAax", "spotify:artist:757aE44tKEUQEqRuT6GnEB", "spotify:artist:3HiuzBlSW7pGDXlSFMhO2g", "spotify:artist:3OoC54nEM3Xl7Kn5hsDdpg", "spotify:artist:6AgTAQt8XS6jRWi4sX7w49", "spotify:artist:45TgXXqMDdF8BkjA83OM7z", "spotify:artist:3Rx4PJ7SP6unkOk5elPUK7", "spotify:artist:0Njy6yR9LykNKYg9yE23QN", "spotify:artist:20qISvAhX20dpIbOOzGK3q", "spotify:artist:31W5EY0aAly4Qieq6OFu6I", "spotify:artist:6lOaHNmL3l3hKDGNf0egfs", "spotify:artist:5QdEbQJ3ylBnc3gsIASAT5", "spotify:artist:757aE44tKEUQEqRuT6GnEB", "spotify:artist:0WK3H9OErSn5zKOkOV5egm", "spotify:artist:1z7b1Pr1rSlvWRzsW3HOrS", "spotify:artist:7c0XG5cIJTrrAgEC3ULPiq", "spotify:artist:6jGMq4yGs7aQzuGsMgVgZR", "spotify:artist:4MCBfE4596Uoi2O4DtmEMz", "spotify:artist:46SHBwWsqBkxI7EeeBEQG7", "spotify:artist:6EPlBSH2RSiettczlz7ihV", "spotify:artist:4FlG0V0jhLO4qGpayFOphj", "spotify:artist:4Gso3d4CscCijv0lmajZWs", "spotify:artist:64KEffDW9EtZ1y2vBYgq8T", "spotify:artist:5SXuuuRpukkTvsLuUknva1", "spotify:artist:2qoQgPAilErOKCwE2Y8wOG", "spotify:artist:0VRj0yCOv2FXJNP47XQnx5", "spotify:artist:3tJoFztHeIJkJWMrx0td2f", "spotify:artist:0hCNtLu0JehylgoiP8L4Gh", "spotify:artist:6icQOAFXDZKsumw3YXyusw", "spotify:artist:2RdwBSPQiwcmiDo9kixcl8", "spotify:artist:2rhFzFmezpnW82MNqEKVry"], "artist_name": ["Metro Boomin", "Drake", "Quavo", "Latto", "Lil Baby", "SoFaygo", "Central Cee", "Gucci Mane", "Lil Uzi Vert", "NLE Choppa", "Key Glock", "Trippie Redd", "Roddy Ricch", "Young Dolph", "Finesse2tymes", "Polo G", "Rod Wave", "Money Man", "Nardo Wick", "Nas", "A Boogie Wit da Hoodie", "Peezy", "G Herbo", "Roddy Ricch", "DDG", "Russ", "Ty Dolla $ign", "Lil Tjay", "Juice WRLD", "Kodak Black", "Sleepy Hallow", "EST Gee", "Don Toliver", "Marshmello", "Baby Keem", "GloRilla", "Quavo", "Moneybagg Yo", "Nicki Minaj", "Lil Yachty", "Pharrell Williams", "Ski Mask The Slump God"], "popularity": [83, 96, 79, 48, 84, 65, 71, 58, 78, 70, 63, 64, 64, 60, 48, 62, 61, 59, 64, 56, 61, 63, 60, 62, 60, 59, 63, 65, 72, 64, 60, 69, 62, 71, 73, 70, 62, 62, 70, 73, 72, 66], "label": ["Republic Records", "OVO / Republic Records", "Quality Control Music/Motown Records", "Streamcut/RCA Records", "Quality Control Music/Motown Records", "Cactus Jack", "Central Cee", "1017/Atlantic", "Generation Now/Atlantic", "Warner Records", "Paper Route EMPIRE", "1400 Entertainment, Inc. / 10K Projects", "Atlantic Records", "Paper Route EMPIRE", "Atlantic Records", "Columbia", "Alamo", "Black Circle / EMPIRE", "Flawless Ent./RCA Records", "Mass Appeal", "Highbridge the Label / Atlantic Records", "#Boyz Entertainment LLC / EMPIRE", "Republic Records", "Atlantic Records", "Epic", "DIEMON", "Atlantic / 10 Summers", "Columbia", "Grade A Productions/Interscope Records", "Atlantic Records", "Winners Circle/RCA Records", "CMG/Warlike/Interscope Records", "Cactus Jack / Atlantic", "Joytime Collective/Grade A Productions/Interscope Records", "pgLane/Columbia", "CMG/Interscope Records", "Quality Control Music/Motown Records", "CMG/N-Less/Interscope Records", "Republic Records", "Quality Control Music/Motown Records", "Columbia", "Republic Records/Victor Victor"], "release_date": ["2022-12-02", "2022-11-04", "2022-10-07", "2022-12-02", "2022-10-14", "2022-11-11", "2022-10-14", "2022-11-15", "2022-10-17", "2022-10-07", "2022-11-17", "2022-10-28", "2022-09-30", "2022-11-17", "2022-12-02", "2022-10-28", "2022-11-10", "2022-10-28", "2022-10-14", "2022-11-29", "2022-10-21", "2022-08-12", "2022-10-07", "2022-11-14", "2022-10-07", "2022-10-14", "2022-10-05", "2022-11-11", "2022-10-28", "2022-09-16", "2022-09-07", "2022-09-16", "2022-11-18", "2022-10-14", "2022-10-28", "2022-09-23", "2022-09-30", "2022-09-22", "2022-08-26", "2022-10-11", "2022-11-18", "2022-10-25"], "total_tracks": [15, 16, 18, 1, 23, 16, 4, 1, 1, 1, 5, 1, 1, 1, 15, 1, 1, 10, 31, 1, 1, 21, 12, 1, 16, 1, 1, 1, 1, 2, 1, 21, 1, 1, 26, 1, 1, 1, 28, 1, 1, 1]}